imgStampTools/__init__.py
imgStampTools/img_stamp.py
imgStampTools/text_stamp.py
imgStampTools-1.0.dist-info/METADATA
imgStampTools-1.0.dist-info/WHEEL
imgStampTools-1.0.dist-info/top_level.txt
imgStampTools-1.0.dist-info/RECORD
