Metadata-Version: 2.1
Name: imgStampTools
Version: 1.0
Summary: lz's utils
Home-page: https://pypi.org/project/imgStampTools/
Author: yazheng
Author-email: 981638732@qq.com
License: UNKNOWN
Platform: UNKNOWN
Classifier: Programming Language :: Python :: 3
